[{"x":"76","y":"68","t":[2415,1246],"v":["Moving","Moving"]},{"x":"10","y":"21","t":[41,54,1788,693,155,530,985],"v":["Moving","Moving","Moving","Moving","Moving","Moving","Moving"]},{"x":"102","y":"62","t":[84,2020,1173,1215,2681,1398,251,666,2016,140],"v":["Moving","Moving","Moving","Moving","Moving","Moving","Moving","Moving","Moving","Moving"]},{"x":"76","y":"42","t":[2476],"v":["Moving"]},{"x":"116","y":"33","t":[151],"v":["Moving"]},{"x":"157","y":"8","t":[165,174,2009,2136,1337,860,323,156,693,618,26,1349,100,41],"v":["Moving","Moving","Moving","Moving","Moving","Moving","Moving","Moving","Moving","Moving","Moving","Moving","Moving","Moving"]},{"x":"25","y":"125","t":[2030,2139,1474,1734,2272,2075,605,113,2051,2135,756,1558],"v":["Moving","Moving","Moving","Moving","Moving","Moving","Moving","Moving","Moving","Moving","Moving","Moving"]},{"x":"64","y":"38","t":[2284],"v":["Moving"]},{"x":"44","y":"44","t":[1310,2443,2237],"v":["Moving","Moving","Moving"]},{"x":"120","y":"44","t":[2187],"v":["Moving"]},{"x":"139","y":"26","t":[1125],"v":["Moving"]}]