[{"x":"210","y":"102","t":[612,613,624,641,645,1896,2484,1264,513,1834,2193,511,835,460,787,1565,331,252,696,600,831,751,794,836,164,2133,739,779,537],"v":["Moving","Moving","Moving","Moving","Moving","Moving","Moving","Moving","Moving","Moving","Moving","Moving","Moving","Moving","Moving","Moving","Moving","Moving","Moving","Moving","Moving","Moving","Moving","Moving","Moving","Moving","Moving","Moving","Moving"]},{"x":"86","y":"80","t":[1,634,53,675,824,875,1941,201,272,310,2152,1194,374,438,2285,443,493,584,571,2590,2602,1331,71,2627,668,613,317,485,625,2289,655,658,2168,591,2665,113,2223,595,654,3,645,488,112,890,2203,2680,446],"v":["Moving","Moving","Moving","Moving","Moving","Moving","Moving","Moving","Moving","Moving","Moving","Moving","Moving","Moving","Moving","Moving","Moving","Moving","Moving","Moving","Moving","Moving","Moving","Moving","Moving","Moving","Moving","Moving","Moving","Moving","Moving","Moving","Moving","Moving","Moving","Moving","Moving","Moving","Moving","Moving","Moving","Moving","Moving","Moving","Moving","Moving","Moving"]},{"x":"170","y":"102","t":[615,794,809,1307,595,593,2003,613,827],"v":["Moving","Moving","Moving","Moving","Moving","Moving","Moving","Moving","Moving"]},{"x":"131","y":"91","t":[614,638,639,678,694,750,752,764,1990,272,340,1246,443,516,2397,1908,458,1888,509,612,618,634,687,511,310,2590,592,591,641,802,469,2072,2333,514,338,611,1200,2401,842,501,2495,861],"v":["Moving","Moving","Moving","Moving","Moving","Moving","Moving","Moving","Moving","Moving","Moving","Moving","Moving","Moving","Moving","Moving","Moving","Moving","Moving","Moving","Moving","Moving","Moving","Moving","Moving","Moving","Moving","Moving","Moving","Moving","Moving","Moving","Moving","Moving","Moving","Moving","Moving","Moving","Moving","Moving","Moving","Moving"]},{"x":"170","y":"40","t":[1365,1963,1121,1248,1140,1188],"v":["Moving","Moving","Moving","Moving","Moving","Moving"]},{"x":"130","y":"49","t":[626,2484,1291,2599,1881,1647,526,1275,1758,802,861,660,1200],"v":["Moving","Moving","Moving","Moving","Moving","Moving","Moving","Moving","Moving","Moving","Moving","Moving","Moving"]},{"x":"19","y":"29","t":[638,2127,2141,448,576,1465,424],"v":["Moving","Moving","No Ticket Type","Moving","Moving","Moving","Moving"]},{"x":"182","y":"58","t":[662,1258,600,937,669,457,2199],"v":["Moving","Moving","Moving","Moving","Moving","Moving","Moving"]},{"x":"184","y":"6","t":[58,477,2009,1993],"v":["Moving","Moving","Moving","Moving"]},{"x":"120","y":"40","t":[671,64,1263,1337,640,59,196,1749,78,1126],"v":["Moving","Moving","Moving","Moving","Moving","Moving","Moving","Moving","Moving","Moving"]},{"x":"120","y":"102","t":[673,709,1459,865,1847,1868,1888,218,1098,236,1498,1668,1127,1140,2191,1209,1223,1737,1662,1313,577,594,2601,1332,0,193,511,750,1312,1554,601,1194,701,887,1333,1201,215,1425,609,1515,1457,751,309,1387,2612,635,1205,1231,1202],"v":["Moving","Moving","Moving","Moving","Moving","Moving","Moving","Moving","Moving","Moving","Moving","Moving","Moving","Moving","Moving","Moving","Moving","Moving","Moving","Moving","Moving","Moving","Moving","Moving","Moving","Moving","Moving","Moving","Moving","Moving","Moving","Moving","Moving","Moving","Moving","Moving","Moving","Moving","Moving","Moving","Moving","Moving","Moving","Moving","Moving","Moving","Moving","Moving","Moving"]},{"x":"52","y":"40","t":[675,1314,201,1428,1369],"v":["Moving","Moving","Moving","Moving","Moving"]},{"x":"122","y":"150","t":[1401,1264,2205,627],"v":["Moving","Moving","Moving","Moving"]},{"x":"247","y":"40","t":[2489,668,485,694],"v":["Moving","Moving","Moving","Moving"]},{"x":"70","y":"40","t":[1892,2053,1496,408,2540,634,390,2178,1604,694,384],"v":["Moving","Moving","Moving","Moving","Moving","Moving","Moving","Moving","Moving","Moving","Moving"]},{"x":"65","y":"252","t":[2525],"v":["Moving"]},{"x":"131","y":"215","t":[2024],"v":["Moving"]},{"x":"52","y":"102","t":[1174,2208,1272,2326,2493,1245,690,915,1344,1988,2381,192],"v":["Moving","Moving","Moving","Moving","Moving","Moving","Moving","Moving","Moving","Moving","Moving","Moving"]},{"x":"74","y":"209","t":[2236],"v":["Moving"]},{"x":"10","y":"39","t":[1657],"v":["Moving"]},{"x":"129","y":"29","t":[1268,292],"v":["Moving","Moving"]},{"x":"149","y":"88","t":[502,559,593],"v":["Moving","Moving","Moving"]},{"x":"16","y":"198","t":[2405,2385],"v":["Moving","Moving"]},{"x":"143","y":"118","t":[2689],"v":["Moving"]},{"x":"88","y":"178","t":[2212],"v":["Moving"]},{"x":"63","y":"13","t":[1211],"v":["Moving"]},{"x":"86","y":"102","t":[1341],"v":["Moving"]},{"x":"122","y":"198","t":[1308,1315],"v":["Moving","Moving"]},{"x":"96","y":"141","t":[2402],"v":["Moving"]},{"x":"10","y":"71","t":[1630],"v":["Moving"]},{"x":"62","y":"50","t":[605,374,1666],"v":["Moving","Moving","Moving"]},{"x":"10","y":"13","t":[1216],"v":["Moving"]},{"x":"251","y":"102","t":[1061],"v":["Moving"]}]